{
  "adventure": {
    "room": [
      {
        "id": 100,
        "start": "true",
        "name": "The forest",
        "short_description": "A green deciduous forest",
        "long_description": "The forest is bright green, but darkened from the thick canopy. you can see a massive redwood to the north",
        "entrance": [
          {
            "id": 101,
            "dir": "N"
          }
        ]
      },
      {
        "id": 101,
        "name": "The big tree",
        "short_description": "A massive redwood",
        "long_description": "A massive redwood looms over the area, casting a giant shadow behind you. there is a river to the east.",
        "entrance": [
          {
            "id": 100,
            "dir": "S"
          },
          {
            "id": 102,
            "dir": "E"
          }
        ],
        "loot": [
          {
            "id": 2
          }
        ]
      },
      {
        "id": 102,
        "name": "The river",
        "short_description": "A medium sized river blocks any entry across",
        "long_description": "A medium sized river rushes past the area, gleaming with fish and minerals. From the look of it, it seems to deep to cross",
        "entrance": [
          {
            "id": 101,
			"dir": "W"
          },
          {
            "id": 103,
            "dir": "N"
          }
        ],
        "loot": [
          {
            "id": 1
          }
        ]
      },
      {
        "id": 103,
        "name": "north river bank",
        "short_description": "The banks of a river, now significantly narrowed",
        "long_description": "The river narrows to a crossable distance, with the water still gushing strongly. To the west is a dead tree ",
        "entrance": [
          {
            "id": 102,
            "dir": "S"
          },
          {
            "id": 104,
            "dir": "W"
          }
        ]
      },
      {
        "id": 104,
        "name": "the dead tree",
        "short_description": "A dead tree sits in the middle of an open field",
        "long_description": "A small dead tree sits alone in the middle of a small field. The tree is covered in moss.",
        "entrance": [
          {
            "id": 103,
            "dir": "E"
          }
        ],
        "loot": [
          {
            "id": 3
          }
        ]
      }
    ],
    "item": [
      {
        "id": 1,
        "name": "stick",
        "desc": "A sharp stick"
      },
      {
        "id": 2,
        "name": "compass",
        "desc": "A worn down yet functional compass"
      },
      {
        "id": 3,
        "name": "moss",
        "desc": "Moldy green moss"
      }
    ]
  }
}